[{"Code":"LNTH","Name":"LANTHEUS HOLDINGS, INC.","TradingViewCode":"NASDAQ:LNTH","Exchange":"NASDAQ"},{"Code":"OCDX","Name":"ORTHO CLINICAL DIAGNOSTICS HOLDINGS PLC","TradingViewCode":"NASDAQ:OCDX","Exchange":"NASDAQ"},{"Code":"CSTL","Name":"CASTLE BIOSCIENCES, INC.","TradingViewCode":"NASDAQ:CSTL","Exchange":"NASDAQ"},{"Code":"MYGN","Name":"MYRIAD GENETICS, INC.","TradingViewCode":"NASDAQ:MYGN","Exchange":"NASDAQ"},{"Code":"NTRA","Name":"NATERA, INC.","TradingViewCode":"NASDAQ:NTRA","Exchange":"NASDAQ"},{"Code":"TXG","Name":"10X GENOMICS, INC.","TradingViewCode":"NASDAQ:TXG","Exchange":"NASDAQ"},{"Code":"DMTK","Name":"DERMTECH, INC.","TradingViewCode":"NASDAQ:DMTK","Exchange":"NASDAQ"},{"Code":"LHDX","Name":"LUCIRA HEALTH, INC.","TradingViewCode":"NASDAQ:LHDX","Exchange":"NASDAQ"},{"Code":"TKNO","Name":"ALPHA TEKNOVA, INC.","TradingViewCode":"NASDAQ:TKNO","Exchange":"NASDAQ"}]