[{"Code":"MCRI","Name":"MONARCH CASINO & RESORT, INC.","TradingViewCode":"NASDAQ:MCRI","Exchange":"NASDAQ"},{"Code":"FLL","Name":"FULL HOUSE RESORTS, INC.","TradingViewCode":"NASDAQ:FLL","Exchange":"NASDAQ"},{"Code":"MGM","Name":"MGM RESORTS INTERNATIONAL","TradingViewCode":"NYSE:MGM","Exchange":"NYSE"},{"Code":"CNTY","Name":"CENTURY CASINOS, INC.","TradingViewCode":"NASDAQ:CNTY","Exchange":"NASDAQ"},{"Code":"MSC","Name":"STUDIO CITY INTERNATIONAL HOLDINGS LIMITED","TradingViewCode":"NYSE:MSC","Exchange":"NYSE"},{"Code":"LVS","Name":"LAS VEGAS SANDS CORP.","TradingViewCode":"NYSE:LVS","Exchange":"NYSE"},{"Code":"WYNN","Name":"WYNN RESORTS, LIMITED","TradingViewCode":"NASDAQ:WYNN","Exchange":"NASDAQ"},{"Code":"ARHN","Name":"ARCHON CORPORATION","TradingViewCode":"OTC:ARHN","Exchange":"OTC"}]