[{"Code":"WSM","Name":"WILLIAMS-SONOMA, INC.","TradingViewCode":"NYSE:WSM","Exchange":"NYSE"},{"Code":"RH","Name":"RH","TradingViewCode":"NYSE:RH","Exchange":"NYSE"},{"Code":"BBBY","Name":"BED BATH & BEYOND INC.","TradingViewCode":"NASDAQ:BBBY","Exchange":"NASDAQ"},{"Code":"HVT","Name":"HAVERTY FURNITURE COMPANIES, INC.","TradingViewCode":"NYSE:HVT","Exchange":"NYSE"},{"Code":"KIRK","Name":"KIRKLAND'S, INC.","TradingViewCode":"NASDAQ:KIRK","Exchange":"NASDAQ"},{"Code":"HOME","Name":"AT HOME GROUP INC.","TradingViewCode":"HOME","Exchange":""}]